sqlahandler/__init__.py
sqlahandler/py.typed
sqlahandler/sqlahandler.py
sqlahandler/sqlahandler0.py
ss_sqlahandler-0.0.25.dist-info/licenses/LICENCE
ss_sqlahandler-0.0.25.dist-info/METADATA
ss_sqlahandler-0.0.25.dist-info/WHEEL
ss_sqlahandler-0.0.25.dist-info/top_level.txt
ss_sqlahandler-0.0.25.dist-info/RECORD
