Metadata-Version: 2.4
Name: ss-sqlahandler
Version: 0.0.25
Summary: Thin wrapper for sqlalchemy core with support for Pandas
Author-email: Julian Briggs <julian.briggs@sheffield.ac.uk>
License-Expression: MIT
Project-URL: Homepage, https://github.com/pypa/ss-sqlahandler
Project-URL: Issues, https://github.com/pypa/ss-sqlahandler/issues
Classifier: Programming Language :: Python :: 3
Classifier: Operating System :: OS Independent
Requires-Python: >=3.12
License-File: LICENCE
Requires-Dist: mysql-connector-python
Requires-Dist: pandas
Requires-Dist: sqlalchemy
Requires-Dist: pymysql
Requires-Dist: mysqlclient
Requires-Dist: configargparse
Requires-Dist: cloud-sql-python-connector[pymysql]
Provides-Extra: dev
Requires-Dist: black; extra == "dev"
Requires-Dist: mypy; extra == "dev"
Requires-Dist: pandas-stubs; extra == "dev"
Requires-Dist: pytest-mock; extra == "dev"
Requires-Dist: pylint-pytest; extra == "dev"
Requires-Dist: radon; extra == "dev"
Requires-Dist: pytest-cov; extra == "dev"
Requires-Dist: types-pymysql; extra == "dev"
Requires-Dist: pytest; extra == "dev"
Requires-Dist: twine; extra == "dev"
Requires-Dist: pip; extra == "dev"
Requires-Dist: build; extra == "dev"
Dynamic: license-file
